{
    "manifestVersion": 1,
    "id": "datadog-integration",
    "version": "1.0.0",
    "name": "Datadog Service Hooks Integration for Azure DevOps",
    "publisher": "Datadog",
    "description": "Send Azure DevOps Service Hooks to Datadog, the monitoring and analytics platform for modern cloud environments",
    "targets": [
        {
            "id": "Microsoft.VisualStudio.Services.Integration"
        }
    ],    
    "icons": {
        "default": "images/service-logo.png"
    },
    "categories": [
        "Azure Pipelines",
	"Azure Boards",
	"Azure Repos",
	"Azure Artifacts"
    ],
    "tags": [
        "monitoring",
        "datadog",
        "events",
	"dashboard",
	"alert"
    ],
   
    "content": {
        "details": {
            "path": "overview.md"
        }
    },
    "links": {
        "getstarted": {
            "uri": "https://docs.microsoft.com/en-us/azure/devops/service-hooks/services/datadog?view=azure-devops"
        },
        "learn": {
            "uri": "https://www.docs.datadoghq.com"
        },
        "support": {
            "uri": "https://www.datadoghq.com/support"
        },
	"privacypolicy": {
            "uri": "https://www.datadoghq.com/legal/privacy"
        },
        "license": {
            "uri": "https://www.datadoghq.com/legal/msa"
        }
    },
    "branding": {
        "color": "rgb(120, 71, 166)",
        "theme": "dark"
    },

    "galleryFlags": [
        "Preview",
	"Public"
    ]

}